traksentinel-0.3.8.dev0.dist-info/licenses/LICENSE
traksentinel_simplecli/__init__.py
traksentinel_simplecli/cli.py
traksentinel-0.3.8.dev0.dist-info/METADATA
traksentinel-0.3.8.dev0.dist-info/WHEEL
traksentinel-0.3.8.dev0.dist-info/entry_points.txt
traksentinel-0.3.8.dev0.dist-info/top_level.txt
traksentinel-0.3.8.dev0.dist-info/RECORD
