Metadata-Version: 2.4
Name: traksentinel
Version: 0.3.8.dev0
Summary: TrakSentinel: OSV-based vulnerability scanner for Python projects
Author-email: Eder Ramos Rosales <eder.ramos.developer@gmail.com>
License: MIT License
Project-URL: Homepage, https://gitlab.com/eder2597/traksentinel
Project-URL: Documentation, https://gitlab.com/eder2597/traksentinel/-/blob/main/README.md
Project-URL: Changelog, https://gitlab.com/eder2597/traksentinel/-/commits/main
Project-URL: Issues, https://gitlab.com/eder2597/traksentinel/-/issues
Project-URL: Source, https://gitlab.com/eder2597/traksentinel
Keywords: security,vulnerability,scanner,python,osv,dependency,audit,cli,open source,pip
Classifier: Development Status :: 4 - Beta
Classifier: Intended Audience :: Developers
Classifier: Intended Audience :: Information Technology
Classifier: Intended Audience :: System Administrators
Classifier: Natural Language :: English
Classifier: Operating System :: POSIX :: Linux
Classifier: Operating System :: Microsoft :: Windows
Classifier: Operating System :: MacOS
Classifier: Programming Language :: Python :: 3
Classifier: Programming Language :: Python :: 3.7
Classifier: Programming Language :: Python :: 3.8
Classifier: Programming Language :: Python :: 3.9
Classifier: Programming Language :: Python :: 3.10
Classifier: Programming Language :: Python :: 3.11
Classifier: Programming Language :: Python :: 3.12
Classifier: Programming Language :: Python :: 3.13
Classifier: Topic :: Security
Requires-Python: >=3.7
License-File: LICENSE
Requires-Dist: requests
Requires-Dist: pyfiglet
Provides-Extra: test
Requires-Dist: pytest; extra == "test"
Provides-Extra: dev
Requires-Dist: pyfiglet; extra == "dev"
Dynamic: license-file
